LICENSE
MANIFEST.in
README.md
conftest.py
setup.py
tox.ini
iosnoop/__init__.py
iosnoop/consts.py
iosnoop/csv.py
iosnoop/filters.py
iosnoop/heatmap.py
iosnoop/main.py
iosnoop/parser.py
iosnoop/plotter.py
iosnoop/utils.py
iosnoop_tool.egg-info/PKG-INFO
iosnoop_tool.egg-info/SOURCES.txt
iosnoop_tool.egg-info/dependency_links.txt
iosnoop_tool.egg-info/entry_points.txt
iosnoop_tool.egg-info/requires.txt
iosnoop_tool.egg-info/top_level.txt
tests/fixtures/iosnoop-sample-bytes.png
tests/fixtures/iosnoop-sample-comm.png
tests/fixtures/iosnoop-sample-with-basedate.png
tests/fixtures/iosnoop-sample.log
tests/fixtures/iosnoop-sample.png
tests/fixtures/iosnoop-small.log